Metadata-Version: 2.1
Name: bquadpy
Version: 0.16.10
Summary: Numerical integration, quadrature for various domains
Home-page: https://github.com/Brishen/bquadpy
Author: Brishen Hawkins
Author-email: brishen.hawkins@gmail.com
License: GPL-3.0-or-later
Project-URL: Code, https://github.com/Brishen/bquadpy
Project-URL: Issues, https://github.com/Brishen/bquadpy/issues
Keywords: mathematics,physics,engineering,quadrature,cubature,integration,numerical integration
Classifier: Development Status :: 4 - Beta
Classifier: Intended Audience :: Science/Research
Classifier: License :: OSI Approved :: GNU General Public License v3 or later (GPLv3+)
Classifier: Operating System :: OS Independent
Classifier: Programming Language :: Python
Classifier: Programming Language :: Python :: 3
Classifier: Programming Language :: Python :: 3.7
Classifier: Programming Language :: Python :: 3.8
Classifier: Programming Language :: Python :: 3.9
Classifier: Programming Language :: Python :: 3.10
Classifier: Topic :: Scientific/Engineering
Classifier: Topic :: Scientific/Engineering :: Mathematics
Requires-Python: >=3.7
License-File: LICENSE
Requires-Dist: ndim
Requires-Dist: numpy
Requires-Dist: orthopy (<0.10,>=0.9)
Requires-Dist: scipy
Requires-Dist: sympy
Requires-Dist: importlib-metadata ; python_version < "3.8"
Provides-Extra: all
Requires-Dist: matplotlib ; extra == 'all'
Requires-Dist: vtk ; extra == 'all'
Provides-Extra: plot
Requires-Dist: matplotlib ; extra == 'plot'
Requires-Dist: vtk ; extra == 'plot'
